pagerduty/manifest.toml
pagerduty/pagerDuty.py
opsbox_pagerduty_output-0.1.4.dist-info/LICENCE.txt
opsbox_pagerduty_output-0.1.4.dist-info/METADATA
opsbox_pagerduty_output-0.1.4.dist-info/WHEEL
opsbox_pagerduty_output-0.1.4.dist-info/entry_points.txt
opsbox_pagerduty_output-0.1.4.dist-info/top_level.txt
opsbox_pagerduty_output-0.1.4.dist-info/RECORD
